vocus_api/__init__.py
vocus_api/vocus.py
vocus_api-0.0.2.dist-info/LICENSE
vocus_api-0.0.2.dist-info/METADATA
vocus_api-0.0.2.dist-info/WHEEL
vocus_api-0.0.2.dist-info/top_level.txt
vocus_api-0.0.2.dist-info/RECORD
