Metadata-Version: 2.1
Name: vocus-api
Version: 0.0.2
Summary: Python wrapper for Vocus portal using bs4 to parse
Author-email: Jake Thomas <jake@telcocentric.com.au>
License: GNU GENERAL PUBLIC LICENSE
Project-URL: Homepage, https://github.com/telcocentric/vocus_api
Keywords: vocus,api
Classifier: License :: OSI Approved :: GNU General Public License v3 or later (GPLv3+)
Classifier: Programming Language :: Python
Classifier: Programming Language :: Python :: 3
Requires-Python: >=3.9
License-File: LICENSE
Requires-Dist: requests (>=2.28.0)
Requires-Dist: bs4 (==0.0.1)
Provides-Extra: dev
Requires-Dist: vcr ; extra == 'dev'
Requires-Dist: python-dotenv ; extra == 'dev'
Requires-Dist: pytest ; extra == 'dev'
